dabapush_gbq/__init__.py
dabapush_gbq/dabapush_gbq.py
dabapush_gbq/schema_generator.py
dabapush_gbq-0.1.0.dist-info/METADATA
dabapush_gbq-0.1.0.dist-info/WHEEL
dabapush_gbq-0.1.0.dist-info/entry_points.txt
dabapush_gbq-0.1.0.dist-info/RECORD
