Metadata-Version: 2.1
Name: dabapush-gbq
Version: 0.1.0
Summary: A Google BigQuery plug-in for dabapush
License: MIT
Author: Philipp Kessling
Author-email: p.kessling@leibniz-hbi.de
Requires-Python: >=3.12,<4.0
Classifier: License :: OSI Approved :: MIT License
Classifier: Programming Language :: Python :: 3
Classifier: Programming Language :: Python :: 3.12
Classifier: Programming Language :: Python :: 3.13
Requires-Dist: dabapush (==0.4.0a2)
Requires-Dist: google-cloud-bigquery (>=3.27.0,<4.0.0)
Requires-Dist: tqdm
Requires-Dist: ujson
